topsis_vaibhavi_102303784/__init__.py
topsis_vaibhavi_102303784/__main__.py
topsis_vaibhavi_102303784/topsis.py
topsis_vaibhavi_102303784-1.0.0.dist-info/licenses/LICENSE
topsis_vaibhavi_102303784-1.0.0.dist-info/METADATA
topsis_vaibhavi_102303784-1.0.0.dist-info/WHEEL
topsis_vaibhavi_102303784-1.0.0.dist-info/entry_points.txt
topsis_vaibhavi_102303784-1.0.0.dist-info/top_level.txt
topsis_vaibhavi_102303784-1.0.0.dist-info/RECORD
