Metadata-Version: 2.4
Name: Topsis-Vaibhavi-102303784
Version: 1.0.0
Summary: A Python package for TOPSIS (Technique for Order Preference by Similarity to Ideal Solution) analysis
Home-page: https://github.com/vaibhavi/Topsis-Vaibhavi-102303784
Author: Vaibhavi
Author-email: vaibhavi@example.com
Project-URL: Bug Reports, https://github.com/vaibhavi/Topsis-Vaibhavi-102303784/issues
Project-URL: Source, https://github.com/vaibhavi/Topsis-Vaibhavi-102303784
Keywords: topsis,multi-criteria decision making,mcdm,decision analysis,ranking
Classifier: Development Status :: 5 - Production/Stable
Classifier: Intended Audience :: Developers
Classifier: Intended Audience :: Science/Research
Classifier: Topic :: Scientific/Engineering :: Mathematics
Classifier: License :: OSI Approved :: MIT License
Classifier: Programming Language :: Python :: 3
Classifier: Programming Language :: Python :: 3.7
Classifier: Programming Language :: Python :: 3.8
Classifier: Programming Language :: Python :: 3.9
Classifier: Programming Language :: Python :: 3.10
Classifier: Programming Language :: Python :: 3.11
Requires-Python: >=3.7
License-File: LICENSE
Requires-Dist: pandas>=1.0.0
Requires-Dist: numpy>=1.18.0
Requires-Dist: openpyxl>=3.0.0
Dynamic: author
Dynamic: author-email
Dynamic: classifier
Dynamic: description
Dynamic: description-content-type
Dynamic: home-page
Dynamic: keywords
Dynamic: license-file
Dynamic: project-url
Dynamic: requires-dist
Dynamic: requires-python
Dynamic: summary
